tube_toolkit/__init__.py
tube_toolkit/main.py
tube_toolkit/core/__init__.py
tube_toolkit/core/actions.py
tube_toolkit/core/logger.py
tube_toolkit-0.0.12.dist-info/METADATA
tube_toolkit-0.0.12.dist-info/WHEEL
tube_toolkit-0.0.12.dist-info/top_level.txt
tube_toolkit-0.0.12.dist-info/RECORD
